represent/__init__.py
represent/core.py
represent/helper.py
represent/utilities.py
Represent-2.1.dist-info/LICENSE
Represent-2.1.dist-info/METADATA
Represent-2.1.dist-info/WHEEL
Represent-2.1.dist-info/top_level.txt
Represent-2.1.dist-info/RECORD
