Metadata-Version: 2.1
Name: Represent
Version: 2.1
Summary: Create __repr__ automatically or declaratively.
Author-email: Frazer McLean <frazer@frazermclean.co.uk>
License: MIT
Project-URL: Repository, https://github.com/RazerM/represent
Project-URL: Documentation, https://represent.readthedocs.io
Classifier: Development Status :: 5 - Production/Stable
Classifier: License :: OSI Approved :: MIT License
Classifier: Programming Language :: Python :: 3 :: Only
Classifier: Programming Language :: Python :: 3.8
Classifier: Programming Language :: Python :: 3.9
Classifier: Programming Language :: Python :: 3.10
Classifier: Programming Language :: Python :: 3.11
Classifier: Programming Language :: Python :: 3.12
Requires-Python: >=3.8
License-File: LICENSE
Provides-Extra: test
Requires-Dist: ipython; extra == "test"
Requires-Dist: pytest; extra == "test"
Requires-Dist: rich; extra == "test"
Provides-Extra: docstest
Requires-Dist: parver; extra == "docstest"
Requires-Dist: sphinx; extra == "docstest"
Requires-Dist: furo; extra == "docstest"
